webint_owner/__init__.py
webint_owner/templates/__init__.py
webint_owner/templates/claim.html
webint_owner/templates/claimed.html
webint_owner/templates/index.html
webint_owner/templates/signin.html
webint_owner/templates/signout.html
webint_owner/templates/unauthorized.html
webint_owner-0.0.26.dist-info/METADATA
webint_owner-0.0.26.dist-info/entry_points.txt
webint_owner-0.0.26.dist-info/WHEEL
webint_owner-0.0.26.dist-info/RECORD
