Metadata-Version: 2.1
Name: webint-owner
Version: 0.0.26
Summary: manage your website's ownership details
License: AGPL-3.0-or-later
Author: Angelo Gladding
Author-email: angelo@ragt.ag
Requires-Python: >=3.10,<3.11
Classifier: License :: OSI Approved :: GNU Affero General Public License v3 or later (AGPLv3+)
Classifier: Programming Language :: Python :: 3
Classifier: Programming Language :: Python :: 3.10
Requires-Dist: httpsig (>=1.3.0,<2.0.0)
Requires-Dist: webint (>=0.0)
